MANIFEST.in
README
setup.py
cryoproxy/__init__.py
cryoproxy/cryoproxy.py
cryoproxy.egg-info/PKG-INFO
cryoproxy.egg-info/SOURCES.txt
cryoproxy.egg-info/dependency_links.txt
cryoproxy.egg-info/entry_points.txt
cryoproxy.egg-info/requires.txt
cryoproxy.egg-info/top_level.txt