Metadata-Version: 1.0
Name: cryoproxy
Version: 2017.4.26
Summary: Cryostream asynchronous serial port proxy daemon based on asyncio
Home-page: https://hg.3lp.cx/cryoproxy
Author: Vadim Dyadkin
Author-email: diadkin@esrf.fr
License: GPL
Platform: UNKNOWN
